<!DOCTYPE suite SYSTEM "http://testng.org/testng-1.0.dtd" >
<suite
	name="Orion TimeSheet Automation - Verify Submit functionality in New Timesheet">

	<!-- Note : If Build tool is Maven in Jenkins, default directory of the 
		extent report changes from /test-output folder to <workspace>/target/surefire-reports -->


	<listeners>
		<listener class-name="com.orion.qa.Listeners.ExtentReportListener" />
		<listener class-name="com.orion.qa.Listeners.TestNGtoJIRAListener" />
	</listeners>
	
	<!-- NEW TIMESHEET CANCEL --> 
	<test name="OrionTimeSheet_Chrome_Test_NewTimeSheet_CancelFunctionality">
		<parameter name="Browser" value="chrome" />
		<parameter name="ClassName" value="Test_NewTimeSheet_CancelFunctionality" />
		<classes>
			<class name="com.orion.qa.testcases.Test_NewTimeSheet_CancelFunctionality" />
		</classes>
	</test>  
	

	<!-- NEW TIMESHEET SUBMIT -->
	<test name="OrionTimeSheet_Chrome_Test_NewTimeSheet_SubmitFunctionality">
		<parameter name="Browser" value="chrome" />
		<parameter name="ClassName" value="Test_NewTimeSheet_SubmitFunctionality" />
		
		<classes>
			<class name="com.orion.qa.testcases.Test_NewTimeSheet_SubmitFunctionality" />
		</classes>
	</test>

</suite>